{"event": {"tournament": {"name": "FIFA World Cup, Qualification CAF, Group F", "slug": "fifa-world-cup-qualification-caf-group-f", "category": {"name": "Africa", "slug": "africa", "sport": {"name": "Football", "slug": "football", "id": 1}, "id": 1466, "flag": "africa"}, "uniqueTournament": {"name": "World Championship Qual. CAF ", "slug": "world-championship-qual-caf", "primaryColorHex": "#9a1133", "secondaryColorHex": "#c11541", "category": {"name": "Africa", "slug": "africa", "sport": {"name": "Football", "slug": "football", "id": 1}, "id": 1466, "flag": "africa"}, "userCount": 56364, "id": 13, "country": {}, "hasEventPlayerStatistics": false, "crowdsourcingEnabled": false, "hasPerformanceGraphFeature": false, "displayInverseHomeAwayTeams": false}, "priority": 506, "competitionType": 1, "id": 7247}, "season": {"name": "FIFA World Cup, Qualification CAF 2025", "editor": false, "id": 56249, "year": "2025"}, "roundInfo": {"round": 2}, "customId": "aVbslVb", "status": {"code": 100, "description": "Ended", "type": "finished"}, "winnerCode": 2, "homeTeam": {"name": "Burundi", "slug": "burundi", "shortName": "Burundi", "gender": "M", "sport": {"name": "Football", "slug": "football", "id": 1}, "userCount": 3982, "manager": {"name": "Etienne Nadyiragije", "slug": "etienne-nadyiragije", "shortName": "E. Nadyiragije", "id": 793337, "country": {"alpha2": "TZ", "name": "Tanzania"}}, "foundationDate": {}, "nameCode": "BDI", "ranking": 142, "disabled": false, "national": true, "type": 0, "id": 4750, "country": {"alpha2": "BI", "name": "Burundi"}, "subTeams": [], "fullName": "Burundi", "teamColors": {"primary": "#ff0000", "secondary": "#00a04d", "text": "#00a04d"}, "foundationDateTimestamp": 1474156800}, "awayTeam": {"name": "Gabon", "slug": "gabon", "shortName": "Gabon", "gender": "M", "sport": {"name": "Football", "slug": "football", "id": 1}, "userCount": 9229, "manager": {"name": "Thierry Mouyouma", "slug": "thierry-mouyouma", "shortName": "T. Mouyouma", "id": 802747, "country": {"alpha2": "GA", "name": "Gabon"}}, "venue": {"city": {"name": "Franceville"}, "stadium": {"name": "Stade de Franceville", "capacity": 20000}, "id": 2834, "country": {"alpha2": "GA", "name": "Gabon"}}, "foundationDate": {}, "nameCode": "GAB", "ranking": 86, "national": true, "type": 0, "id": 4761, "country": {"alpha2": "GA", "name": "Gabon"}, "subTeams": [], "fullName": "Gabon", "teamColors": {"primary": "#fef101", "secondary": "#0f22ca", "text": "#0f22ca"}, "foundationDateTimestamp": -255225600}, "homeScore": {"current": 1, "display": 1, "period1": 0, "period2": 1, "normaltime": 1}, "awayScore": {"current": 2, "display": 2, "period1": 1, "period2": 1, "normaltime": 2}, "time": {"currentPeriodStartTimestamp": 1700403019}, "changes": {"changes": ["status.code", "status.description", "status.type"], "changeTimestamp": 1700406043}, "hasGlobalHighlights": false, "hasEventPlayerStatistics": false, "detailId": 4, "crowdsourcingDataDisplayEnabled": false, "id": 11797916, "defaultPeriodCount": 2, "defaultPeriodLength": 45, "defaultOvertimeLength": 15, "crowdsourcingEnabled": false, "currentPeriodStartTimestamp": 1700403019, "startTimestamp": 1700398800, "slug": "gabon-burundi", "finalResultOnly": false, "hasBet365LiveStream": true, "bet365ExcludedCountryCodes": ["??", "AE", "AN", "BH", "CU", "DJ", "DZ", "EG", "IQ", "IR", "JO", "KM", "KP", "KW", "LB", "LY", "MA", "MR", "OM", "PS", "QA", "SA", "SD", "SO", "SY", "TD", "TN", "VE", "YE", "GR", "RU", "CH", "CA"], "fanRatingEvent": false, "showTotoPromo": false, "isEditor": false}}