{"event": {"tournament": {"name": "European Championship, Qualification Group I", "slug": "european-championship-qualification-group-i", "category": {"name": "Europe", "slug": "europe", "sport": {"name": "Football", "slug": "football", "id": 1}, "id": 1465, "flag": "europe"}, "uniqueTournament": {"name": "European Championship, Qualification", "slug": "european-championship-qualification", "primaryColorHex": "#182026", "secondaryColorHex": "#730000", "category": {"name": "Europe", "slug": "europe", "sport": {"name": "Football", "slug": "football", "id": 1}, "id": 1465, "flag": "europe"}, "userCount": 224172, "id": 27, "country": {}, "hasEventPlayerStatistics": true, "crowdsourcingEnabled": false, "hasPerformanceGraphFeature": false, "displayInverseHomeAwayTeams": false}, "priority": 535, "competitionType": 1, "id": 5347}, "season": {"name": "European Championship 2024, Qualification", "editor": false, "seasonCoverageInfo": {}, "id": 46599, "year": "2024"}, "roundInfo": {"round": 7}, "customId": "FObsZTb", "status": {"code": 0, "description": "Not started", "type": "notstarted"}, "venue": {"city": {"name": "Felcsut"}, "stadium": {"name": "Pancho Arena"}, "id": 16555, "country": {"alpha2": "HU", "name": "Hungary"}}, "referee": {"name": "Anthony Taylor", "slug": "taylor-anthony", "yellowCards": 1871, "redCards": 48, "yellowRedCards": 35, "games": 479, "sport": {"id": 1, "slug": "football", "name": "Football"}, "id": 69853, "country": {"alpha2": "EN", "name": "England"}}, "homeTeam": {"name": "Israel", "slug": "israel", "shortName": "Israel", "gender": "M", "sport": {"name": "Football", "slug": "football", "id": 1}, "userCount": 13767, "manager": {"name": "Alon Hazan", "slug": "alon-hazan", "shortName": "A. Hazan", "id": 786711, "country": {"alpha2": "IL", "name": "Israel"}}, "nameCode": "ISR", "ranking": 71, "disabled": false, "national": true, "type": 0, "id": 4480, "country": {"alpha2": "IL", "name": "Israel"}, "subTeams": [], "fullName": "Israel", "teamColors": {"primary": "#7bafde", "secondary": "#ffffff", "text": "#ffffff"}}, "awayTeam": {"name": "Switzerland", "slug": "switzerland", "shortName": "Switzerland", "gender": "M", "sport": {"name": "Football", "slug": "football", "id": 1}, "userCount": 88079, "manager": {"name": "Murat Yakin", "slug": "murat-yakin", "shortName": "M. Yakin", "id": 67424, "country": {"alpha2": "CH", "name": "Switzerland"}}, "foundationDate": {}, "nameCode": "SUI", "ranking": 14, "disabled": false, "national": true, "type": 0, "id": 4699, "country": {"alpha2": "CH", "name": "Switzerland"}, "subTeams": [], "fullName": "Switzerland", "teamColors": {"primary": "#ff0000", "secondary": "#ffffff", "text": "#ffffff"}, "foundationDateTimestamp": -2358460800}, "homeScore": {}, "awayScore": {}, "time": {}, "changes": {"changeTimestamp": 0}, "hasGlobalHighlights": false, "detailId": 1, "crowdsourcingDataDisplayEnabled": false, "id": 11733451, "defaultPeriodCount": 2, "defaultPeriodLength": 45, "defaultOvertimeLength": 15, "crowdsourcingEnabled": false, "startTimestamp": 1700077500, "slug": "switzerland-israel", "finalResultOnly": false, "fanRatingEvent": false, "seasonStatisticsType": "overall", "showTotoPromo": false, "isEditor": false}}